.gitignore
LICENSE
MANIFEST.in
README.md
pyproject.toml
setup.cfg
setup.py
src/simplepygamemenus/__init__.py
src/simplepygamemenus/font.ttf
src/simplepygamemenus/menu.py
src/simplepygamemenus/rect.png
src/simplepygamemenus.egg-info/PKG-INFO
src/simplepygamemenus.egg-info/SOURCES.txt
src/simplepygamemenus.egg-info/dependency_links.txt
src/simplepygamemenus.egg-info/requires.txt
src/simplepygamemenus.egg-info/top_level.txt