Metadata-Version: 2.1
Name: simplepygamemenus
Version: 0.1.2
Summary: A package for making simple menus for your python games!
Home-page: https://github.com/LeonardoFerrisi/simplepygamemenus-gitrepo
Author: Leonardo Ferrisi
Author-email: ferrisil@union.edu
License: MIT
Project-URL: repository, https://github.com/LeonardoFerrisi/simplepygamemenus-gitrepo
Platform: UNKNOWN
Classifier: Programming Language :: Python :: 3
Classifier: License :: OSI Approved :: MIT License
Classifier: Operating System :: OS Independent
Requires-Python: >=3.8
License-File: LICENSE
